CloudFlare/__init__.py
CloudFlare/api_decode_from_web.py
CloudFlare/api_extras.py
CloudFlare/api_v4.py
CloudFlare/cloudflare.py
CloudFlare/exceptions.py
CloudFlare/logging_helper.py
CloudFlare/network.py
CloudFlare/read_configs.py
CloudFlare/utils.py
cli4/__init__.py
cli4/__main__.py
cli4/cli4.1
cli4/cli4.py
cli4/converters.py
cloudflare-2.9.11.data/data/share/man/man1/cli4.1
examples/__init__.py
examples/example_account_rules_lists_items.py
examples/example_always_use_https.py
examples/example_are_zones_ipv6.py
examples/example_are_zones_ipv6_simple.py
examples/example_certificates.py
examples/example_create_zone_and_populate.py
examples/example_custom_hostnames.py
examples/example_delete_zone_entry.py
examples/example_dns_export.py
examples/example_dns_import.py
examples/example_dnssec_settings.py
examples/example_graphql.py
examples/example_graphql.sh
examples/example_ips.py
examples/example_list_api_from_web.py
examples/example_page_rules.py
examples/example_page_rules.sh
examples/example_paging_thru_zones.py
examples/example_paging_thru_zones.sh
examples/example_proxied.py
examples/example_settings.py
examples/example_show_account_email.py
examples/example_update_dynamic_dns.py
examples/example_user.py
examples/example_user_tokens.py
examples/example_with_usage.py
examples/example_zone_search.sh
examples/example_zones.py
cloudflare-2.9.11.dist-info/LICENSE
cloudflare-2.9.11.dist-info/METADATA
cloudflare-2.9.11.dist-info/PKG-INFO 2
cloudflare-2.9.11.dist-info/WHEEL
cloudflare-2.9.11.dist-info/dependency_links 2.txt
cloudflare-2.9.11.dist-info/entry_points.txt
cloudflare-2.9.11.dist-info/top_level.txt
cloudflare-2.9.11.dist-info/RECORD
