Metadata-Version: 2.1
Name: cloudflare
Version: 2.9.11
Summary: Python wrapper for the Cloudflare v4 API
Home-page: https://github.com/cloudflare/python-cloudflare
Author: Martin J. Levy
Author-email: martin@cloudflare.com
License: MIT
Keywords: cloudflare
Platform: UNKNOWN
Classifier: Development Status :: 5 - Production/Stable
Classifier: Intended Audience :: Developers
Classifier: Topic :: Software Development :: Libraries :: Python Modules
Classifier: License :: OSI Approved :: MIT License
Classifier: Programming Language :: Python :: 3
Classifier: Programming Language :: Python :: 3.2
Classifier: Programming Language :: Python :: 3.3
Classifier: Programming Language :: Python :: 3.4
Classifier: Programming Language :: Python :: 3.5
Classifier: Programming Language :: Python :: 3.6
Classifier: Programming Language :: Python :: 3.7
Classifier: Programming Language :: Python :: 3.8
License-File: LICENSE
